README.rst
setup.cfg
setup.py
plenario_stream_kinesis_producer/__init__.py
plenario_stream_kinesis_producer/defaults.py
plenario_stream_kinesis_producer/listeners.py
plenario_stream_kinesis_producer.egg-info/PKG-INFO
plenario_stream_kinesis_producer.egg-info/SOURCES.txt
plenario_stream_kinesis_producer.egg-info/dependency_links.txt
plenario_stream_kinesis_producer.egg-info/requires.txt
plenario_stream_kinesis_producer.egg-info/top_level.txt