Metadata-Version: 1.2
Name: plenario-stream-kinesis-producer
Version: 0.0.1
Summary: Converts Plenario Stream Core signals into kinesis records
Home-page: https://github.com/UrbanCCD-UChicago/plenario-stream-kinesis-producer
Author: Jesus Bracho
Author-email: jbracho@uchicago.edu
License: GPLv3
Keywords: plenario
Platform: UNKNOWN
Classifier: Development Status :: 3 - Alpha
Classifier: License :: OSI Approved :: GNU General Public License v3 (GPLv3)
Classifier: Programming Language :: Python :: 3.6
Requires-Python: >=3.6
